face_symmetrizer/__init__.py
face_symmetrizer/faceSym.py
face_symmetrizer/main.py
face_symmetrizer/py.typed
face_symmetrizer-1.8.1.dist-info/LICENSE
face_symmetrizer-1.8.1.dist-info/METADATA
face_symmetrizer-1.8.1.dist-info/WHEEL
face_symmetrizer-1.8.1.dist-info/entry_points.txt
face_symmetrizer-1.8.1.dist-info/top_level.txt
face_symmetrizer-1.8.1.dist-info/RECORD
