Metadata-Version: 2.1
Name: face-symmetrizer
Version: 1.8.1
Summary: Easy symmetrizer for an image contained face(s)
Home-page: https://github.com/eggplants/face-symmetrizer
Author: eggplants
Author-email: w10776e8w@yahoo.co.jp
Maintainer: eggplants
Maintainer-email: w10776e8w@yahoo.co.jp
License: MIT
Platform: UNKNOWN
Classifier: License :: OSI Approved :: MIT License
Classifier: Programming Language :: Python :: 3
Classifier: Programming Language :: Python :: 3 :: Only
Classifier: Programming Language :: Python :: 3.7
Classifier: Programming Language :: Python :: 3.8
Classifier: Programming Language :: Python :: 3.9
Classifier: Programming Language :: Python :: 3.10
Requires-Python: >=3.7
License-File: LICENSE
Requires-Dist: Pillow (>=9.0.1)
Requires-Dist: PyQt5 (>=5.15.6)
Requires-Dist: face-recognition (>=1.3.0)
Requires-Dist: matplotlib (>=3.5.1)
Requires-Dist: numpy (>=1.22.2)
Requires-Dist: types-Pillow (>=9.0.6)
Provides-Extra: dev
Requires-Dist: notebook ; extra == 'dev'
Requires-Dist: pre-commit ; extra == 'dev'
Requires-Dist: setuptools ; extra == 'dev'
Requires-Dist: types-setuptools (>=57.4.7) ; extra == 'dev'
Requires-Dist: wheel ; extra == 'dev'
